langsheet_package/main.py
langsheet-0.0.0.dist-info/LICENSE
langsheet-0.0.0.dist-info/METADATA
langsheet-0.0.0.dist-info/WHEEL
langsheet-0.0.0.dist-info/top_level.txt
langsheet-0.0.0.dist-info/RECORD
